allenpoly/__init__.py
allenpoly/run.py
allenpoly/callbacks/__init__.py
allenpoly/callbacks/poly_track_metrics.py
allenpoly/commands/__init__.py
allenpoly/commands/train.py
allenpoly-0.0.5.dist-info/LICENSE.txt
allenpoly-0.0.5.dist-info/METADATA
allenpoly-0.0.5.dist-info/WHEEL
allenpoly-0.0.5.dist-info/entry_points.txt
allenpoly-0.0.5.dist-info/top_level.txt
allenpoly-0.0.5.dist-info/RECORD
