Metadata-Version: 2.1
Name: allenpoly
Version: 0.0.5
Summary: An library to use AllenNLP library in Polyaxon environment.
Home-page: https://bitbucket.org/evidenceprime/allenpoly
Author: Evidence Prime Sp. z o.o.
Author-email: mateusz.pieniak@evidenceprime.com
License: BSD
Keywords: allennlp,polyaxon
Platform: UNKNOWN
Requires-Python: >=3.6
Requires-Dist: python-dateutil (<2.8.1,>=2.1)
Requires-Dist: docutils (<0.16,>=0.10)
Requires-Dist: rhea (==0.5.4)
Requires-Dist: allennlp (>=0.9.0)
Requires-Dist: polyaxon-client (>=0.5.6)
